{"data":{"AKIR#0":{"getConnectCode":{"user":{"displayName":"woke moralist","connectCode":{"code":"AKIR#0"},"rankedNetplayProfile":{"id":"RANKED_SINGLES-TdfDnCbMy9deI5WzKwxABCemeFp1-season-3","ratingOrdinal":2521.951745378353,"ratingUpdateCount":172,"wins":145,"losses":27,"dailyGlobalPlacement":24,"dailyRegionalPlacement":23,"continent":"NORTH_AMERICA","characters":[{"character":"DONKEY_KONG","gameCount":244},{"character":"LUIGI","gameCount":1},{"character":"FOX","gameCount":17},{"character":"MARTH","gameCount":73},{"character":"CAPTAIN_FALCON","gameCount":16},{"character":"GANONDORF","gameCount":3},{"character":"YOUNG_LINK","gameCount":3},{"character":"SHEIK","gameCount":6},{"character":"PIKACHU","gameCount":2},{"character":"ICE_CLIMBERS","gameCount":1},{"character":"FALCO","gameCount":3},{"character":"DR_MARIO","gameCount":4},{"character":"PEACH","gameCount":1}]}}},"tag":""},"ARTH#977":{"getConnectCode":{"user":{"displayName":"watch the clock","connectCode":{"code":"ARTH#977"},"rankedNetplayProfile":{"id":"RANKED_SINGLES-IYYbajNT3laHo0mrQqTCHNra1I02-season-3","ratingOrdinal":2351.6554628516506,"ratingUpdateCount":99,"wins":73,"losses":26,"dailyGlobalPlacement":109,"dailyRegionalPlacement":null,"continent":"NORTH_AMERICA","characters":[{"character":"DONKEY_KONG","gameCount":221},{"character":"GAME_AND_WATCH","gameCount":1}]}}},"tag":"*hugs*"},"BMOH#898":{"getConnectCode":{"user":{"displayName":"Maslow's Hammer","connectCode":{"code":"BMOH#898"},"rankedNetplayProfile":{"id":"RANKED_SINGLES-xlUcdPPnrjdjrGnWIBgLQabaq4f1-season-3","ratingOrdinal":1888.4090822339367,"ratingUpdateCount":225,"wins":116,"losses":109,"dailyGlobalPlacement":null,"dailyRegionalPlacement":null,"continent":"NORTH_AMERICA","characters":[{"character":"DONKEY_KONG","gameCount":527}]}}},"tag":"BMOHC"},"DONG734":{"getConnectCode":null,"tag":"DongDysfunktion"},"DRAK#892":{"getConnectCode":{"user":{"displayName":"Drakula","connectCode":{"code":"DRAK#892"},"rankedNetplayProfile":{"id":"RANKED_SINGLES-URgS2UFBZXdwp9DEmeAlBQeModZ2-season-3","ratingOrdinal":1686.3331361290261,"ratingUpdateCount":695,"wins":345,"losses":350,"dailyGlobalPlacement":null,"dailyRegionalPlacement":null,"continent":"NORTH_AMERICA","characters":[{"character":"DONKEY_KONG","gameCount":1634}]}}},"tag":""},"DRUM#727":{"getConnectCode":{"user":{"displayName":"Drumbasher004","connectCode":{"code":"DRUM#727"},"rankedNetplayProfile":{"id":"RANKED_SINGLES-w04hOvzpxchYdW08HnIlcdSUoEL2-season-3","ratingOrdinal":791.1742324697398,"ratingUpdateCount":34,"wins":7,"losses":27,"dailyGlobalPlacement":null,"dailyRegionalPlacement":null,"continent":"NORTH_AMERICA","characters":[{"character":"DONKEY_KONG","gameCount":73}]}}},"tag":""},"FAYE#749":{"getConnectCode":{"user":{"displayName":"FishnetF3tish","connectCode":{"code":"FAYE#749"},"rankedNetplayProfile":{"id":"RANKED_SINGLES-gDIbBwuzSdMqwoITRX65efnrsu13-season-3","ratingOrdinal":1777.1365094579098,"ratingUpdateCount":27,"wins":17,"losses":10,"dailyGlobalPlacement":null,"dailyRegionalPlacement":null,"continent":"EUROPE","characters":[{"character":"DONKEY_KONG","gameCount":27},{"character":"MARTH","gameCount":6},{"character":"FOX","gameCount":24}]}}},"tag":"Faye <3"},"GHOS#594":{"getConnectCode":{"user":{"displayName":"MF BOONE","connectCode":{"code":"GHOS#594"},"rankedNetplayProfile":{"id":"RANKED_SINGLES-qfqzwXz7yPT7xQHvCHJIkIShj0v1-season-3","ratingOrdinal":1460.8910017428666,"ratingUpdateCount":25,"wins":13,"losses":12,"dailyGlobalPlacement":null,"dailyRegionalPlacement":null,"continent":"EUROPE","characters":[{"character":"DONKEY_KONG","gameCount":48},{"character":"CAPTAIN_FALCON","gameCount":5},{"character":"FALCO","gameCount":1},{"character":"JIGGLYPUFF","gameCount":1}]}}},"tag":"Gorillionaire"},"GRAN#711":{"getConnectCode":{"user":{"displayName":"granny","connectCode":{"code":"GRAN#711"},"rankedNetplayProfile":{"id":"RANKED_SINGLES-gcZswUL6lZXmEEd8jBP1emisj192-season-3","ratingOrdinal":1100,"ratingUpdateCount":0,"wins":0,"losses":0,"dailyGlobalPlacement":null,"dailyRegionalPlacement":null,"continent":null,"characters":[]}}},"tag":"granny"},"GWAG#662":{"getConnectCode":{"user":{"displayName":"big guy","connectCode":{"code":"GWAG#662"},"rankedNetplayProfile":{"id":"RANKED_SINGLES-ZggxNMashiM2ef1NGewI5Inxk9j2-season-3","ratingOrdinal":1495.8332339635247,"ratingUpdateCount":409,"wins":207,"losses":202,"dailyGlobalPlacement":null,"dailyRegionalPlacement":null,"continent":"NORTH_AMERICA","characters":[{"character":"DONKEY_KONG","gameCount":948},{"character":"FALCO","gameCount":1}]}}},"tag":"G wag"},"HAON#749":{"getConnectCode":{"user":{"displayName":"CMGB","connectCode":{"code":"HAON#749"},"rankedNetplayProfile":{"id":"RANKED_SINGLES-IwuVbCwAywfHxHYW9TBpFsG4fLt2-season-3","ratingOrdinal":895.2916062212387,"ratingUpdateCount":73,"wins":19,"losses":54,"dailyGlobalPlacement":null,"dailyRegionalPlacement":null,"continent":"NORTH_AMERICA","characters":[{"character":"DONKEY_KONG","gameCount":155},{"character":"FALCO","gameCount":1},{"character":"CAPTAIN_FALCON","gameCount":1}]}}},"tag":""},"IUDK#240":{"getConnectCode":{"user":{"displayName":"SHREK FANBOY","connectCode":{"code":"IUDK#240"},"rankedNetplayProfile":{"id":"RANKED_SINGLES-jEEcRnET3xfn5eFVaHlZw757ir42-season-3","ratingOrdinal":2162.2631410928943,"ratingUpdateCount":201,"wins":150,"losses":51,"dailyGlobalPlacement":null,"dailyRegionalPlacement":34,"continent":"EUROPE","characters":[{"character":"DONKEY_KONG","gameCount":471}]}}},"tag":"iudking"},"JADE#771":{"getConnectCode":{"user":{"displayName":"Jadestone","connectCode":{"code":"JADE#771"},"rankedNetplayProfile":{"id":"RANKED_SINGLES-aLfTAr8CJqR2i0CnXceN2O5efTE3-season-3","ratingOrdinal":1274.9236124228676,"ratingUpdateCount":157,"wins":67,"losses":90,"dailyGlobalPlacement":null,"dailyRegionalPlacement":null,"continent":"NORTH_AMERICA","characters":[{"character":"DONKEY_KONG","gameCount":344}]}}},"tag":"Jadestone"},"JEFF#69":{"getConnectCode":{"user":{"displayName":"JEFF","connectCode":{"code":"JEFF#69"},"rankedNetplayProfile":{"id":"RANKED_SINGLES-TKG9GJCc4eh06GN4qZxsGC6DklL2-season-3","ratingOrdinal":995.5435002187364,"ratingUpdateCount":3,"wins":0,"losses":3,"dailyGlobalPlacement":null,"dailyRegionalPlacement":null,"continent":"NORTH_AMERICA","characters":[{"character":"DONKEY_KONG","gameCount":8}]}}},"tag":""},"JELO#460":{"getConnectCode":{"user":{"displayName":"Jell0","connectCode":{"code":"JELO#460"},"rankedNetplayProfile":{"id":"RANKED_SINGLES-0hc1pcnfyRXGcUiedxBlBvJePTE2-season-3","ratingOrdinal":1616.5659667341804,"ratingUpdateCount":111,"wins":58,"losses":53,"dailyGlobalPlacement":null,"dailyRegionalPlacement":null,"continent":"NORTH_AMERICA","characters":[{"character":"DONKEY_KONG","gameCount":197},{"character":"PEACH","gameCount":6},{"character":"LUIGI","gameCount":6},{"character":"FOX","gameCount":22},{"character":"FALCO","gameCount":2},{"character":"MARTH","gameCount":1},{"character":"SHEIK","gameCount":12},{"character":"SAMUS","gameCount":1},{"character":"ICE_CLIMBERS","gameCount":3},{"character":"GANONDORF","gameCount":1}]}}},"tag":"Jell0"},"JOE#867":{"getConnectCode":{"user":{"displayName":"Yabuki Joe","connectCode":{"code":"JOE#867"},"rankedNetplayProfile":{"id":"RANKED_SINGLES-M6IroP09nyXDi05DlbKpIFXqful1-season-3","ratingOrdinal":1478.9261820727088,"ratingUpdateCount":6,"wins":5,"losses":1,"dailyGlobalPlacement":null,"dailyRegionalPlacement":null,"continent":"EUROPE","characters":[{"character":"DONKEY_KONG","gameCount":11},{"character":"FOX","gameCount":1}]}}},"tag":"Yabuki Joe"},"JUNE#771":{"getConnectCode":{"user":{"displayName":"unemployedgamer","connectCode":{"code":"JUNE#771"},"rankedNetplayProfile":{"id":"RANKED_SINGLES-otfB7vuullhX69MCoEK61oXlqcF3-season-3","ratingOrdinal":2299.1877491598134,"ratingUpdateCount":22,"wins":21,"losses":1,"dailyGlobalPlacement":null,"dailyRegionalPlacement":null,"continent":"NORTH_AMERICA","characters":[{"character":"DONKEY_KONG","gameCount":46},{"character":"DR_MARIO","gameCount":1}]}}},"tag":""},"KEYS#901":{"getConnectCode":{"user":{"displayName":"keystone","connectCode":{"code":"KEYS#901"},"rankedNetplayProfile":{"id":"RANKED_SINGLES-RioME7UTIfbgtjKnCguoSY868u22-season-3","ratingOrdinal":1614.5986647427735,"ratingUpdateCount":499,"wins":252,"losses":247,"dailyGlobalPlacement":null,"dailyRegionalPlacement":null,"continent":"NORTH_AMERICA","characters":[{"character":"DONKEY_KONG","gameCount":1129}]}}},"tag":"Keystone"},"MAYO#795":{"getConnectCode":{"user":{"displayName":"Mayonaisaurus","connectCode":{"code":"MAYO#795"},"rankedNetplayProfile":{"id":"RANKED_SINGLES-OdDOKrrNcRQ8yZPb7eOL5UAyQw42-season-3","ratingOrdinal":1809.7295173229422,"ratingUpdateCount":441,"wins":221,"losses":220,"dailyGlobalPlacement":null,"dailyRegionalPlacement":null,"continent":"NORTH_AMERICA","characters":[{"character":"DONKEY_KONG","gameCount":1003},{"character":"CAPTAIN_FALCON","gameCount":10}]}}},"tag":"The Mayo"},"OTTR#444":{"getConnectCode":{"user":{"displayName":"Bananananananan","connectCode":{"code":"OTTR#444"},"rankedNetplayProfile":{"id":"RANKED_SINGLES-LeEPndLVrmd6yX0sUUmKbrpVobj2-season-3","ratingOrdinal":1100,"ratingUpdateCount":0,"wins":0,"losses":0,"dailyGlobalPlacement":null,"dailyRegionalPlacement":null,"continent":null,"characters":[]}}},"tag":"OtterFodder"},"PLAY#128":{"getConnectCode":{"user":{"displayName":"BadPlay","connectCode":{"code":"PLAY#128"},"rankedNetplayProfile":{"id":"RANKED_SINGLES-n2VjzJeM1oSp0VYwYMViM12MLqa2-season-3","ratingOrdinal":1227.004928951739,"ratingUpdateCount":18,"wins":9,"losses":9,"dailyGlobalPlacement":null,"dailyRegionalPlacement":null,"continent":"EUROPE","characters":[{"character":"DONKEY_KONG","gameCount":10},{"character":"GANONDORF","gameCount":31}]}}},"tag":"BadPlay"},"SHEESH#0":{"getConnectCode":{"user":{"displayName":"Kong Analyst","connectCode":{"code":"SHEESH#0"},"rankedNetplayProfile":{"id":"RANKED_SINGLES-99rjcxyqOWf6KeiKhAXcMzvYgTs1-season-3","ratingOrdinal":1100,"ratingUpdateCount":0,"wins":0,"losses":0,"dailyGlobalPlacement":null,"dailyRegionalPlacement":null,"continent":null,"characters":[]}}},"tag":"Andy"},"SUMO#959":{"getConnectCode":{"user":{"displayName":"asl;","connectCode":{"code":"SUMO#959"},"rankedNetplayProfile":{"id":"RANKED_SINGLES-nvjbAtmW6EhI3MM8rXLTSDUj1fg2-season-3","ratingOrdinal":1647.7862505856792,"ratingUpdateCount":84,"wins":47,"losses":37,"dailyGlobalPlacement":null,"dailyRegionalPlacement":null,"continent":"EUROPE","characters":[{"character":"DONKEY_KONG","gameCount":181},{"character":"JIGGLYPUFF","gameCount":1},{"character":"CAPTAIN_FALCON","gameCount":7}]}}},"tag":"asl;"},"TAZA#0":{"getConnectCode":{"user":{"displayName":"Taza","connectCode":{"code":"TAZA#0"},"rankedNetplayProfile":{"id":"RANKED_SINGLES-UZT59POignbbo5SMfrhz7zkBFbT2-season-3","ratingOrdinal":2048.412911327294,"ratingUpdateCount":44,"wins":31,"losses":13,"dailyGlobalPlacement":null,"dailyRegionalPlacement":null,"continent":"NORTH_AMERICA","characters":[{"character":"DONKEY_KONG","gameCount":99}]}}},"tag":"Taza"},"THRN#111":{"getConnectCode":{"user":{"displayName":"suzanne.obj","connectCode":{"code":"THRN#111"},"rankedNetplayProfile":{"id":"RANKED_SINGLES-1XKWGUlslfVdca3NuczjMuq0aiC2-season-3","ratingOrdinal":1490.5804833574534,"ratingUpdateCount":13,"wins":8,"losses":5,"dailyGlobalPlacement":null,"dailyRegionalPlacement":null,"continent":"NORTH_AMERICA","characters":[{"character":"DONKEY_KONG","gameCount":33}]}}},"tag":"Thorneman"},"XAN#108":{"getConnectCode":{"user":{"displayName":"Sun Wukong","connectCode":{"code":"XAN#108"},"rankedNetplayProfile":{"id":"RANKED_SINGLES-Ure1qt2dzQSGggf0r5Kr2JlWKyE3-season-3","ratingOrdinal":1764.4354356164654,"ratingUpdateCount":259,"wins":176,"losses":83,"dailyGlobalPlacement":null,"dailyRegionalPlacement":23,"continent":"OCEANIA","characters":[{"character":"DONKEY_KONG","gameCount":531},{"character":"FOX","gameCount":49},{"character":"FALCO","gameCount":19}]}}},"tag":""}},"updatedAt":1752273764}